setup.py
ore/__init__.py
ore.tokenauth.egg-info/PKG-INFO
ore.tokenauth.egg-info/SOURCES.txt
ore.tokenauth.egg-info/dependency_links.txt
ore.tokenauth.egg-info/namespace_packages.txt
ore.tokenauth.egg-info/not-zip-safe
ore.tokenauth.egg-info/requires.txt
ore.tokenauth.egg-info/top_level.txt
ore/tokenauth/__init__.py
ore/tokenauth/auth.py
ore/tokenauth/browser.py
ore/tokenauth/configure.zcml
ore/tokenauth/interfaces.py
ore/tokenauth/token.py