Metadata-Version: 1.0
Name: ore.tokenauth
Version: 0.3.5
Summary: A secure session authentication scheme based on signed tokens.
Home-page: http://svn.objectrealms.net/view/public/browser/ore.tokenauth/trunk
Author: Kapil Thangavelu
Author-email: kapil.foss@gmail.com
License: GPL
Keywords: zope authentication
Platform: UNKNOWN
Classifier: Programming Language :: Python
Classifier: Environment :: Web Environment
Classifier: License :: OSI Approved :: Zope Public License
Classifier: Topic :: Internet :: WWW/HTTP :: WSGI :: Application
Classifier: Framework :: Zope3
